LICENSE
MANIFEST.in
README.rst
setup.cfg
setup.py
versioneer.py
tests/__init__.py
tests/test_general.py
tpRigToolkit/__init__.py
tpRigToolkit/config/__init__.py
tpRigToolkit/config/__version__.py
tpRigToolkit/config/_version.py
tpRigToolkit/config/development/tpRigToolkit-controls.yml
tpRigToolkit/config/development/tpRigToolkit-core.yml
tpRigToolkit/config/development/tpRigToolkit-libs-controlrig.yml
tpRigToolkit/config/development/tpRigToolkit-names.yml
tpRigToolkit/config/development/tpRigToolkit-naming.yml
tpRigToolkit/config/production/tpRigToolkit-controls.yml
tpRigToolkit/config/production/tpRigToolkit-core.yml
tpRigToolkit/config/production/tpRigToolkit-libs-controlrig.yml
tpRigToolkit/config/production/tpRigToolkit-names.yml
tpRigToolkit/config/production/tpRigToolkit-naming.yml
tpRigToolkit_config.egg-info/PKG-INFO
tpRigToolkit_config.egg-info/SOURCES.txt
tpRigToolkit_config.egg-info/dependency_links.txt
tpRigToolkit_config.egg-info/not-zip-safe
tpRigToolkit_config.egg-info/requires.txt
tpRigToolkit_config.egg-info/top_level.txt