Metadata-Version: 2.1
Name: tpRigToolkit-config
Version: 0.0.4
Summary: tpRigToolkit module that contains configuration files
Home-page: https://github.com/tpRigToolkit/tpRigToolkit-config
Author: Tomas Poveda
Author-email: tpovedatd@gmail.com
License: MIT
Platform: UNKNOWN
Provides-Extra: dev
Provides-Extra: test
